<?xml version="1.0" encoding="UTF-8"?>
<document>
<simulation randomSeed="-2500851785706843246" name="checkDiffusionReachesEquilibriumInCylinder" outputfolder="./unitTests" log="DEBUG" comment="null" >
	<timer stepSize="0.1" endOfSimulation="100.0" />
 	<speciesLib />
 	<compartment name="cylinder" >
		<shape class="Cylinder" >
			<dimension name="R" isCyclic="false" targetResolution="null" min="0.0" max="4.9E-324" />
 			<dimension name="THETA" isCyclic="false" targetResolution="null" min="0.0" max="4.9E-324" />
 			<dimension name="Z" isCyclic="false" targetResolution="null" min="0.0" max="4.9E-324" />
 		</shape>
		<solutes >
			<solute name="solute" concentration="1.9131647598729862,1.9131647598729862,1.9131647598729862%1.9175839832573833,1.9175839832573833,1.9175839832573833;1.9175839832573833,1.9175839832573833,1.9175839832573833;1.9175839832573833,1.9175839832573833,1.9175839832573833%1.9260850760373638,1.9260850760373638,1.9260850760373638;1.9260850760373638,1.9260850760373638,1.9260850760373638;1.9260850760373638,1.9260850760373638,1.9260850760373638;1.9260850760373638,1.9260850760373638,1.9260850760373638;1.9260850760373638,1.9260850760373638,1.9260850760373638%1.9380219441041289,1.9380219441041289,1.9380219441041289;1.9380219441041289,1.9380219441041289,1.9380219441041289;1.9380219441041289,1.9380219441041289,1.9380219441041289;1.9380219441041289,1.9380219441041289,1.9380219441041289;1.9380219441041289,1.9380219441041289,1.9380219441041289;1.9380219441041289,1.9380219441041289,1.9380219441041289;1.9380219441041289,1.9380219441041289,1.9380219441041289%1.9524944328292668,1.9524944328292668,1.9524944328292668;1.9524944328292668,1.9524944328292668,1.9524944328292668;1.9524944328292668,1.9524944328292668,1.9524944328292668;1.9524944328292668,1.9524944328292668,1.9524944328292668;1.9524944328292668,1.9524944328292668,1.9524944328292668;1.9524944328292668,1.9524944328292668,1.9524944328292668;1.9524944328292668,1.9524944328292668,1.9524944328292668;1.9524944328292668,1.9524944328292668,1.9524944328292668;1.9524944328292668,1.9524944328292668,1.9524944328292668%1.968424209431272,1.968424209431272,1.968424209431272;1.968424209431272,1.968424209431272,1.968424209431272;1.968424209431272,1.968424209431272,1.968424209431272;1.968424209431272,1.968424209431272,1.968424209431272;1.968424209431272,1.968424209431272,1.968424209431272;1.968424209431272,1.968424209431272,1.968424209431272;1.968424209431272,1.968424209431272,1.968424209431272;1.968424209431272,1.968424209431272,1.968424209431272;1.968424209431272,1.968424209431272,1.968424209431272;1.968424209431272,1.968424209431272,1.968424209431272;1.968424209431272,1.968424209431272,1.968424209431272%1.9846451152192868,1.9846451152192868,1.9846451152192868;1.9846451152192868,1.9846451152192868,1.9846451152192868;1.9846451152192868,1.9846451152192868,1.9846451152192868;1.9846451152192868,1.9846451152192868,1.9846451152192868;1.9846451152192868,1.9846451152192868,1.9846451152192868;1.9846451152192868,1.9846451152192868,1.9846451152192868;1.9846451152192868,1.9846451152192868,1.9846451152192868;1.9846451152192868,1.9846451152192868,1.9846451152192868;1.9846451152192868,1.9846451152192868,1.9846451152192868;1.9846451152192868,1.9846451152192868,1.9846451152192868;1.9846451152192868,1.9846451152192868,1.9846451152192868;1.9846451152192868,1.9846451152192868,1.9846451152192868;1.9846451152192868,1.9846451152192868,1.9846451152192868" />
 		</solutes>
		<agents />
 		<processManagers >
			<process name="DR solver" class="SolveDiffusionTransient" priority="1" firstStep="35.10000000000023" />
 		</processManagers>
	</compartment>
</simulation>
</document>
