<?xml version="1.0" encoding="UTF-8"?>
<document>
<simulation randomSeed="-4219568829829592845" name="checkDiffusionReachesEquilibriumInCylinder" outputfolder="./unitTests" log="DEBUG" comment="null" >
	<timer stepSize="0.1" endOfSimulation="100.0" />
 	<speciesLib />
 	<compartment name="cylinder" >
		<shape class="Cylinder" >
			<dimension name="R" isCyclic="false" targetResolution="null" min="0.0" max="4.9E-324" />
 			<dimension name="THETA" isCyclic="false" targetResolution="null" min="0.0" max="4.9E-324" />
 			<dimension name="Z" isCyclic="false" targetResolution="null" min="0.0" max="4.9E-324" />
 		</shape>
		<solutes >
			<solute name="solute" concentration="0.9835891632323985,0.9835891632323985,0.9835891632323985%1.0341431357411544,1.0341431357411544,1.0341431357411544;1.0341431357411544,1.0341431357411544,1.0341431357411544;1.0341431357411544,1.0341431357411544,1.0341431357411544%1.1318464432906299,1.1318464432906299,1.1318464432906299;1.1318464432906299,1.1318464432906299,1.1318464432906299;1.1318464432906299,1.1318464432906299,1.1318464432906299;1.1318464432906299,1.1318464432906299,1.1318464432906299;1.1318464432906299,1.1318464432906299,1.1318464432906299%1.2699831069341645,1.2699831069341645,1.2699831069341645;1.2699831069341645,1.2699831069341645,1.2699831069341645;1.2699831069341645,1.2699831069341645,1.2699831069341645;1.2699831069341645,1.2699831069341645,1.2699831069341645;1.2699831069341645,1.2699831069341645,1.2699831069341645;1.2699831069341645,1.2699831069341645,1.2699831069341645;1.2699831069341645,1.2699831069341645,1.2699831069341645%1.4387921689504042,1.4387921689504042,1.4387921689504042;1.4387921689504042,1.4387921689504042,1.4387921689504042;1.4387921689504042,1.4387921689504042,1.4387921689504042;1.4387921689504042,1.4387921689504042,1.4387921689504042;1.4387921689504042,1.4387921689504042,1.4387921689504042;1.4387921689504042,1.4387921689504042,1.4387921689504042;1.4387921689504044,1.4387921689504044,1.4387921689504044;1.4387921689504044,1.4387921689504044,1.4387921689504044;1.4387921689504044,1.4387921689504044,1.4387921689504044%1.6260187439023968,1.6260187439023968,1.6260187439023968;1.6260187439023968,1.6260187439023968,1.6260187439023968;1.6260187439023968,1.6260187439023968,1.6260187439023968;1.6260187439023968,1.6260187439023968,1.6260187439023968;1.6260187439023968,1.6260187439023968,1.6260187439023968;1.6260187439023968,1.6260187439023968,1.6260187439023968;1.6260187439023968,1.6260187439023968,1.6260187439023968;1.626018743902397,1.626018743902397,1.626018743902397;1.626018743902397,1.626018743902397,1.626018743902397;1.626018743902397,1.626018743902397,1.626018743902397;1.626018743902397,1.626018743902397,1.626018743902397%1.8178207077212913,1.8178207077212913,1.8178207077212913;1.8178207077212913,1.8178207077212913,1.8178207077212913;1.8178207077212913,1.8178207077212913,1.8178207077212913;1.8178207077212913,1.8178207077212913,1.8178207077212913;1.8178207077212911,1.8178207077212911,1.8178207077212911;1.8178207077212911,1.8178207077212911,1.8178207077212911;1.8178207077212911,1.8178207077212911,1.8178207077212911;1.8178207077212911,1.8178207077212911,1.8178207077212911;1.8178207077212913,1.8178207077212913,1.8178207077212913;1.8178207077212913,1.8178207077212913,1.8178207077212913;1.8178207077212913,1.8178207077212913,1.8178207077212913;1.8178207077212913,1.8178207077212913,1.8178207077212913;1.8178207077212913,1.8178207077212913,1.8178207077212913" />
 		</solutes>
		<agents />
 		<processManagers >
			<process name="DR solver" class="SolveDiffusionTransient" priority="1" firstStep="10.999999999999977" />
 		</processManagers>
	</compartment>
</simulation>
</document>
