<?xml version="1.0" encoding="UTF-8"?>
<document>
<simulation randomSeed="-2331283535375844629" name="checkDiffusionReachesEquilibriumInCylinder" outputfolder="./unitTests" log="DEBUG" comment="null" >
	<timer stepSize="0.1" endOfSimulation="100.0" />
 	<speciesLib />
 	<compartment name="cylinder" >
		<shape class="Cylinder" >
			<dimension name="R" isCyclic="false" targetResolution="null" min="0.0" max="4.9E-324" />
 			<dimension name="THETA" isCyclic="false" targetResolution="null" min="0.0" max="4.9E-324" />
 			<dimension name="Z" isCyclic="false" targetResolution="null" min="0.0" max="4.9E-324" />
 		</shape>
		<solutes >
			<solute name="solute" concentration="1.6326014961899837,1.6326014961899837,1.6326014961899837%1.6512933585435252,1.6512933585435252,1.6512933585435252;1.6512933585435252,1.6512933585435252,1.6512933585435252;1.6512933585435252,1.6512933585435252,1.6512933585435252%1.68725243570677,1.68725243570677,1.68725243570677;1.68725243570677,1.68725243570677,1.68725243570677;1.68725243570677,1.68725243570677,1.68725243570677;1.68725243570677,1.68725243570677,1.68725243570677;1.68725243570677,1.68725243570677,1.68725243570677%1.7377493002945301,1.7377493002945301,1.7377493002945301;1.7377493002945301,1.7377493002945301,1.7377493002945301;1.7377493002945301,1.7377493002945301,1.7377493002945301;1.7377493002945301,1.7377493002945301,1.7377493002945301;1.7377493002945301,1.7377493002945301,1.7377493002945301;1.7377493002945301,1.7377493002945301,1.7377493002945301;1.7377493002945301,1.7377493002945301,1.7377493002945301%1.7989792441813355,1.7989792441813355,1.7989792441813355;1.7989792441813355,1.7989792441813355,1.7989792441813355;1.7989792441813355,1.7989792441813355,1.7989792441813355;1.7989792441813355,1.7989792441813355,1.7989792441813355;1.7989792441813355,1.7989792441813355,1.7989792441813355;1.7989792441813355,1.7989792441813355,1.7989792441813355;1.7989792441813355,1.7989792441813355,1.7989792441813355;1.7989792441813355,1.7989792441813355,1.7989792441813355;1.7989792441813355,1.7989792441813355,1.7989792441813355%1.8663816697395563,1.8663816697395563,1.8663816697395563;1.8663816697395563,1.8663816697395563,1.8663816697395563;1.8663816697395563,1.8663816697395563,1.8663816697395563;1.8663816697395563,1.8663816697395563,1.8663816697395563;1.8663816697395563,1.8663816697395563,1.8663816697395563;1.8663816697395563,1.8663816697395563,1.8663816697395563;1.8663816697395563,1.8663816697395563,1.8663816697395563;1.8663816697395563,1.8663816697395563,1.8663816697395563;1.8663816697395563,1.8663816697395563,1.8663816697395563;1.8663816697395563,1.8663816697395563,1.8663816697395563;1.8663816697395563,1.8663816697395563,1.8663816697395563%1.9350216261009392,1.9350216261009392,1.9350216261009392;1.9350216261009392,1.9350216261009392,1.9350216261009392;1.9350216261009392,1.9350216261009392,1.9350216261009392;1.9350216261009392,1.9350216261009392,1.9350216261009392;1.9350216261009392,1.9350216261009392,1.9350216261009392;1.9350216261009392,1.9350216261009392,1.9350216261009392;1.9350216261009392,1.9350216261009392,1.9350216261009392;1.9350216261009392,1.9350216261009392,1.9350216261009392;1.9350216261009392,1.9350216261009392,1.9350216261009392;1.9350216261009392,1.9350216261009392,1.9350216261009392;1.9350216261009392,1.9350216261009392,1.9350216261009392;1.9350216261009392,1.9350216261009392,1.9350216261009392;1.9350216261009392,1.9350216261009392,1.9350216261009392" />
 		</solutes>
		<agents />
 		<processManagers >
			<process name="DR solver" class="SolveDiffusionTransient" priority="1" firstStep="21.00000000000003" />
 		</processManagers>
	</compartment>
</simulation>
</document>
