<?xml version="1.0" encoding="UTF-8"?>
<document>
<simulation randomSeed="4199692913927479760" name="checkDiffusionReachesEquilibriumInCylinder" outputfolder="./unitTests" log="DEBUG" comment="null" >
	<timer stepSize="0.1" endOfSimulation="200.0" />
 	<speciesLib />
 	<compartment name="cylinder" >
		<shape class="Cylinder" >
			<dimension name="R" isCyclic="false" targetResolution="null" min="0.0" max="4.9E-324" />
 			<dimension name="THETA" isCyclic="false" targetResolution="null" min="0.0" max="4.9E-324" />
 			<dimension name="Z" isCyclic="false" targetResolution="null" min="0.0" max="4.9E-324" />
 		</shape>
		<solutes >
			<solute name="solute" concentration="1.9781942170355749,1.9781942170355749,1.9781942170355749%1.9787632056104372,1.9787632056104372,1.9787632056104372;1.9787632056104372,1.9787632056104372,1.9787632056104372;1.9787632056104372,1.9787632056104372,1.9787632056104372%1.9798789124296523,1.9798789124296523,1.9798789124296523;1.9798789124296523,1.9798789124296523,1.9798789124296523;1.9798789124296523,1.9798789124296523,1.9798789124296523;1.9798789124296523,1.9798789124296523,1.9798789124296523;1.9798789124296523,1.9798789124296523,1.9798789124296523%1.9814977653492085,1.9814977653492085,1.9814977653492085;1.9814977653492085,1.9814977653492085,1.9814977653492085;1.9814977653492085,1.9814977653492085,1.9814977653492085;1.9814977653492085,1.9814977653492085,1.9814977653492085;1.9814977653492085,1.9814977653492085,1.9814977653492085;1.9814977653492085,1.9814977653492085,1.9814977653492085;1.9814977653492085,1.9814977653492085,1.9814977653492085%1.9835567832196699,1.9835567832196699,1.9835567832196699;1.9835567832196699,1.9835567832196699,1.9835567832196699;1.9835567832196699,1.9835567832196699,1.9835567832196699;1.9835567832196699,1.9835567832196699,1.9835567832196699;1.9835567832196699,1.9835567832196699,1.9835567832196699;1.9835567832196699,1.9835567832196699,1.9835567832196699;1.9835567832196699,1.9835567832196699,1.9835567832196699;1.9835567832196699,1.9835567832196699,1.9835567832196699;1.9835567832196699,1.9835567832196699,1.9835567832196699%1.9859763066106608,1.9859763066106608,1.9859763066106608;1.9859763066106608,1.9859763066106608,1.9859763066106608;1.9859763066106608,1.9859763066106608,1.9859763066106608;1.9859763066106608,1.9859763066106608,1.9859763066106608;1.9859763066106608,1.9859763066106608,1.9859763066106608;1.9859763066106608,1.9859763066106608,1.9859763066106608;1.9859763066106608,1.9859763066106608,1.9859763066106608;1.9859763066106608,1.9859763066106608,1.9859763066106608;1.9859763066106608,1.9859763066106608,1.9859763066106608;1.9859763066106608,1.9859763066106608,1.9859763066106608;1.9859763066106608,1.9859763066106608,1.9859763066106608%1.9886634419834246,1.9886634419834246,1.9886634419834246;1.9886634419834246,1.9886634419834246,1.9886634419834246;1.9886634419834246,1.9886634419834246,1.9886634419834246;1.9886634419834246,1.9886634419834246,1.9886634419834246;1.9886634419834246,1.9886634419834246,1.9886634419834246;1.9886634419834246,1.9886634419834246,1.9886634419834246;1.9886634419834246,1.9886634419834246,1.9886634419834246;1.9886634419834246,1.9886634419834246,1.9886634419834246;1.9886634419834246,1.9886634419834246,1.9886634419834246;1.9886634419834246,1.9886634419834246,1.9886634419834246;1.9886634419834246,1.9886634419834246,1.9886634419834246;1.9886634419834246,1.9886634419834246,1.9886634419834246;1.9886634419834246,1.9886634419834246,1.9886634419834246%1.991516062588427,1.991516062588427,1.991516062588427;1.991516062588427,1.991516062588427,1.991516062588427;1.991516062588427,1.991516062588427,1.991516062588427;1.991516062588427,1.991516062588427,1.991516062588427;1.991516062588427,1.991516062588427,1.991516062588427;1.991516062588427,1.991516062588427,1.991516062588427;1.991516062588427,1.991516062588427,1.991516062588427;1.991516062588427,1.991516062588427,1.991516062588427;1.991516062588427,1.991516062588427,1.991516062588427;1.991516062588427,1.991516062588427,1.991516062588427;1.991516062588427,1.991516062588427,1.991516062588427;1.991516062588427,1.991516062588427,1.991516062588427;1.991516062588427,1.991516062588427,1.991516062588427;1.991516062588427,1.991516062588427,1.991516062588427;1.991516062588427,1.991516062588427,1.991516062588427%1.994427184454092,1.994427184454092,1.994427184454092;1.994427184454092,1.994427184454092,1.994427184454092;1.994427184454092,1.994427184454092,1.994427184454092;1.994427184454092,1.994427184454092,1.994427184454092;1.994427184454092,1.994427184454092,1.994427184454092;1.994427184454092,1.994427184454092,1.994427184454092;1.994427184454092,1.994427184454092,1.994427184454092;1.994427184454092,1.994427184454092,1.994427184454092;1.994427184454092,1.994427184454092,1.994427184454092;1.994427184454092,1.994427184454092,1.994427184454092;1.994427184454092,1.994427184454092,1.994427184454092;1.994427184454092,1.994427184454092,1.994427184454092;1.994427184454092,1.994427184454092,1.994427184454092;1.994427184454092,1.994427184454092,1.994427184454092;1.994427184454092,1.994427184454092,1.994427184454092;1.994427184454092,1.994427184454092,1.994427184454092;1.994427184454092,1.994427184454092,1.994427184454092%1.9972895194198053,1.9972895194198053,1.9972895194198053;1.9972895194198053,1.9972895194198053,1.9972895194198053;1.9972895194198053,1.9972895194198053,1.9972895194198053;1.9972895194198053,1.9972895194198053,1.9972895194198053;1.9972895194198053,1.9972895194198053,1.9972895194198053;1.9972895194198053,1.9972895194198053,1.9972895194198053;1.9972895194198053,1.9972895194198053,1.9972895194198053;1.9972895194198053,1.9972895194198053,1.9972895194198053;1.9972895194198053,1.9972895194198053,1.9972895194198053;1.9972895194198053,1.9972895194198053,1.9972895194198053;1.9972895194198053,1.9972895194198053,1.9972895194198053;1.9972895194198053,1.9972895194198053,1.9972895194198053;1.9972895194198053,1.9972895194198053,1.9972895194198053;1.9972895194198053,1.9972895194198053,1.9972895194198053;1.9972895194198053,1.9972895194198053,1.9972895194198053;1.9972895194198053,1.9972895194198053,1.9972895194198053;1.9972895194198053,1.9972895194198053,1.9972895194198053;1.9972895194198053,1.9972895194198053,1.9972895194198053;1.9972895194198053,1.9972895194198053,1.9972895194198053" />
 		</solutes>
		<agents />
 		<processManagers >
			<process name="DR solver" class="SolveDiffusionTransient" priority="1" firstStep="95.19999999999887" />
 		</processManagers>
	</compartment>
</simulation>
</document>
