<?xml version="1.0" encoding="UTF-8"?>
<document>
<simulation randomSeed="-5407081380539861152" name="checkDiffusionReachesEquilibriumInSphere" outputfolder="./unitTests" log="DEBUG" comment="null" >
	<timer stepSize="0.1" endOfSimulation="100.0" />
 	<speciesLib />
 	<compartment name="sphere" >
		<shape class="Sphere" >
			<dimension name="R" isCyclic="false" targetResolution="null" min="0.0" max="4.0" />
 			<dimension name="PHI" isCyclic="false" targetResolution="null" min="0.0" max="4.9E-324" />
 			<dimension name="THETA" isCyclic="false" targetResolution="null" min="0.0" max="4.9E-324" />
 		</shape>
		<solutes >
			<solute name="solute" concentration="1.9423954933043386,1.9423954048525969;1.942395493304338,1.9423954048525973%1.9486644403683515,1.948663391467663,1.9486686234810018;1.9486444176330306,1.9486996286992067,1.9486515291659372,1.9486632187541086,1.9487069371794656,1.9485655370274737,1.9487271272804825;1.948658032957327,1.9486537799762753,1.9486655167635145,1.948685926911877,1.9486702206692843,1.9486036840007155,1.9486651096383878,1.948699816030239,1.9486872790034289;1.9486444176330346,1.94869962869924,1.9486515291659323,1.9486632187541086,1.9487069371794707,1.9485655370274402,1.9487271272804787;1.9486644403683409,1.948663391467663,1.9486686234810127%1.9600088621237368,1.9600063897810587,1.9600184686453883;1.959947367886132,1.960130814954089,1.95996340485906,1.960020878862282,1.9600194011905117,1.9601485685756603,1.9596613659937412,1.9601981191456808;1.9601221482677702,1.9605027522001648,1.9590739075891552,1.9602770704117818,1.960102020317257,1.9599469044884645,1.9601016772231763,1.9597592466818756,1.959235808851283,1.9627537732349756,1.9585728435324374,1.959686729402394;1.9594076677871946,1.961225430381105,1.9601846204513285,1.9586665376499828,1.9608526402695625,1.959774256244479,1.9599484880783438,1.9599630963356398,1.960188557135031,1.960717101252918,1.9575575918729708,1.9639425017269239,1.959504267278421,1.9564584833947398,1.9617773628922786;1.9594076677872947,1.961225430380673,1.9601846204526492,1.958666537645453,1.960852640282323,1.959774256221857,1.9599484880960383,1.959963096335641,1.9601885571173339,1.9607171012755427,1.9575575918602086,1.9639425017314545,1.9595042672771001,1.9564584833951717,1.9617773628921784;1.9601221482677744,1.9605027522000487,1.9590739075905752,1.9602770704066739,1.960102020320549,1.9599469044992626,1.9601016772123785,1.959759246678583,1.9592358088563915,1.9627537732335552,1.9585728435325536,1.9596867294023896;1.959947367886148,1.960130814953842,1.9599634048600003,1.9600208788569389,1.9600194011958547,1.96014856857472,1.9596613659939883,1.9601981191456646;1.9600088621236968,1.9600063897810587,1.9600184686454283%1.9742502038881466,1.9742586004347447,1.974219243963017;1.9740555683878556,1.9747287626776213,1.9738942962031485,1.9742747205313926,1.9742235861814788,1.974126928337415,1.9752698986255781,1.9728198724523884,1.9747905114608466;1.9762409384995663,1.9721772189625482,1.9725855956951825,1.977011063249753,1.9729173763003074,1.9747012830962731,1.9737520534110728,1.9748554394767768,1.9731662437817792,1.9780734731233234,1.9661417721314498,1.9790935027018848,1.9802862301898907,1.9683953680477637;1.9540083132304131,2.0179361768400126,1.9335254004622344,2.0014202042529528,1.9602025676659742,1.9793309575387739,1.973456055316628,1.973412536340126,1.9759615549369012,1.972189899690528,1.9754589500993898,1.9769231975854547,1.9592470194098157,2.0153578420895704,1.8947070582499914,2.093391584912484,1.8463863761511183,2.0334525949430815;2.035700780488707,1.8297161610893249,2.128265164852639,1.8564574419093711,2.0465134321463356,1.9368079266846563,1.9914907357970884,1.9666016383588414,1.9781607399060996,1.970868128452726,1.9791367633384387,1.9646698500322324,1.9960045430686006,1.923946320616205,2.083723133969244,1.7627928579396184,2.3188905167141813,1.5235495073402474,2.397153431179178,1.794404581355653;1.8814538925413362,2.195281540432533,1.7351890511465018,2.1575223209161307,1.86345041077056,2.0294649962833637,1.9509747588401174,1.9827160053724613,1.9712957828892137,1.97566301991678,1.973393261271442,1.9735761711535513,1.980468200396405,1.9507795777452681,2.0416706127695226,1.8129599169918664,2.298301413026387,1.437992839149234,2.6737356065421647,1.3274476153970336,2.2457593444494863;2.0357007804889733,1.829716161088567,2.1282651648537314,1.8564574419089903,2.046513432141321,1.9368079267074805,1.9914907357307816,1.9666016385137142,1.9781607396092196,1.9708681288928607,1.9791367628983012,1.964669850329119,1.996004542913721,1.9239463206825165,2.0837231339464175,1.7627928579446341,2.3188905167145606,1.523549507339157,2.3971534311799343,1.794404581355387;1.9540083132302175,2.0179361768406947,1.933525400460099,2.001420204260006,1.9602025676471726,1.9793309575827038,1.9734560552155662,1.9734125365552637,1.9759615545794176,1.9721899000480134,1.975458949884248,1.9769231976865205,1.9592470193658826,2.0153578421083735,1.8947070582429375,2.093391584914618,1.8463863761504369,2.033452594943277;1.9762409384995419,1.9721772189630387,1.972585595692998,1.9770110632530666,1.9729173763077328,1.9747012830503654,1.9737520535208481,1.9748554393670013,1.9731662438276871,1.9780734731158982,1.9661417721281356,1.9790935027040695,1.9802862301894,1.9683953680477881;1.9740555683877137,1.9747287626780656,1.9738942962008907,1.9742747205362303,1.9742235861814788,1.974126928332577,1.9752698986278359,1.972819872451944,1.9747905114609885;1.9742502038884906,1.9742586004347447,1.974219243962673" />
 		</solutes>
		<agents />
 		<processManagers >
			<process name="DR solver" class="SolveDiffusionTransient" priority="1" firstStep="12.099999999999973" />
 		</processManagers>
	</compartment>
</simulation>
</document>
