<?xml version="1.0" encoding="UTF-8"?>
<document>
<simulation randomSeed="4720785593558512314" name="checkDiffusionReachesEquilibriumInSphere" outputfolder="./unitTests" log="DEBUG" comment="null" >
	<timer stepSize="0.1" endOfSimulation="30.0" />
 	<speciesLib />
 	<compartment name="sphere" >
		<shape class="Sphere" >
			<dimension name="R" isCyclic="false" targetResolution="null" min="0.0" max="5.0" />
 			<dimension name="PHI" isCyclic="false" targetResolution="null" min="0.0" max="4.9E-324" />
 			<dimension name="THETA" isCyclic="false" targetResolution="null" min="0.0" max="4.9E-324" />
 		</shape>
		<solutes >
			<solute name="solute" concentration="1.2268911420135851E57%2.4300377870083677E57;4.204194168403649E57,3.317310307334271E57;5.8281172593302754E57,4.330523522538222E57%7.261431110370957E57;1.0373806528769352E58,8.849742957979022E57;2.7756076087870664E58,1.497863192436106E58,1.7052782453669757E58;2.987369593135197E58,3.624227759208784E58,2.85381946629835E58,1.766460191322864E58;3.76974329653881E58,3.525944953540958E58,2.66380258375145E58,2.2018924986210444E58%2.4829093835992098E58;1.8451537908362373E58,2.0968660257533438E58;1.1990114876384763E59,1.27051401302521E58,6.375133760144149E58;4.1302844048009724E57,2.249037694350123E59,9.358284660672743E58,1.912696463406164E58;4.483049029109396E59,0.0,4.270843467732433E59,0.0,2.10825171045013E59;1.3894552597619962E58,6.2548152016385465E59,0.0,3.930039458567558E59,0.0;2.9599206933140697E59,1.6161934678442665E59,2.418625302912199E59,2.635363563195167E59,4.9176974182524907E58,1.6177410685092332E59%9.429229553481093E58;0.0,1.2141979111238482E58;3.1114669187123784E59,0.0,1.5664961085334314E59;0.0,4.996462850399352E59,2.3518256774993337E59,0.0;1.3665886478048581E60,0.0,8.303084078314325E59,0.0,5.477756431455086E59;0.0,3.0261736504970265E60,0.0,1.3107707165517927E60,9.487842775014944E59,0.0;2.9526957381967226E60,0.0,3.0402114931702918E60,0.0,0.0,1.1058958602951676E60;0.0,4.6724237168421866E60,0.0,3.1200082965595943E60,0.0,1.9951597261745957E60,0.0;2.2555015809829797E60,0.0,3.295884029590073E60,0.0,1.9761736664980424E60,0.0,9.762043327830604E59" />
 		</solutes>
		<agents />
 		<processManagers >
			<process name="DR solver" class="SolveDiffusionTransient" priority="1" firstStep="29.100000000000144" />
 		</processManagers>
	</compartment>
</simulation>
</document>
