<?xml version="1.0" encoding="UTF-8"?>
<document>
<simulation randomSeed="3069262428335072456" name="checkDiffusionReachesEquilibriumInSphere" outputfolder="./unitTests" log="DEBUG" comment="null" >
	<timer stepSize="0.1" endOfSimulation="10.0" />
 	<speciesLib />
 	<compartment name="sphere" >
		<shape class="Sphere" >
			<dimension name="R" isCyclic="false" targetResolution="null" min="0.0" max="4.0" />
 			<dimension name="PHI" isCyclic="false" targetResolution="null" min="0.0" max="4.9E-324" />
 			<dimension name="THETA" isCyclic="false" targetResolution="null" min="0.0" max="4.9E-324" />
 		</shape>
		<solutes >
			<solute name="solute" concentration="1.3070144720361232%1.381818757468581;1.3818187572468654,1.3818187576903342;1.3818187574876333,1.3818187574495429%1.5176890737786906;1.5176890719329694,1.5176890756249324;1.5176887491776259,1.517689732310217,1.517688739847895;1.517689307685653,1.5176888464234424,1.5176888152751484,1.5176893257313315;1.5176888774578383,1.517689266212038,1.5176892840042093,1.517688867440907%1.6889302177577017;1.6889302066051424,1.688930228923182;1.6889290949317886,1.6889325265769757,1.6889290317657184;1.6889347639125425,1.6889258697403546,1.6889250431184946,1.6889351942822162;1.6889033296179792,1.6889944036012523,1.688854968668519,1.6889962764082411,1.68890211050008;1.6889576208099772,1.68886363415687,1.6890092251959592,1.6888618321730728,1.6889587764747038;1.6889159100863,1.688956769968099,1.6889178409882817,1.6889179784642319,1.688957462491455,1.6889153445654488" />
 		</solutes>
		<agents />
 		<processManagers >
			<process name="DR solver" class="SolveDiffusionTransient" priority="1" firstStep="4.6" />
 		</processManagers>
	</compartment>
</simulation>
</document>
