<?xml version="1.0" encoding="UTF-8"?>
<document>
<simulation randomSeed="-1075022865808358937" name="checkDiffusionIndifferentForRadiusInSphere" outputfolder="./unitTests" log="DEBUG" comment="null" >
	<timer stepSize="0.1" endOfSimulation="100.0" />
 	<speciesLib />
 	<compartment name="sphere" >
		<shape class="Sphere" >
			<dimension name="R" isCyclic="false" targetResolution="null" min="0.0" max="3.0" />
 			<dimension name="PHI" isCyclic="false" targetResolution="null" min="0.0" max="4.9E-324" />
 			<dimension name="THETA" isCyclic="false" targetResolution="null" min="0.0" max="4.9E-324" />
 		</shape>
		<solutes >
			<solute name="solute" concentration="1.9998183306557464%1.999842415478629;1.999842415478629,1.999842415478629;1.999842415478629,1.999842415478629%1.9998849972917832;1.9998849972917832,1.9998849972917832;1.9998849972917832,1.9998849972917832,1.9998849972917832;1.9998849972917832,1.9998849972917832,1.9998849972917832,1.9998849972917832;1.9998849972917832,1.9998849972917832,1.9998849972917832,1.9998849972917832" />
 		</solutes>
		<agents />
 		<processManagers >
			<process name="DR solver" class="SolveDiffusionTransient" priority="1" firstStep="30.400000000000162" />
 		</processManagers>
	</compartment>
</simulation>
</document>
